rest_choice/__init__.py
rest_choice/views.py
rest_choices/__init__.py
rest_choices/views.py
django_rest_choices-0.0.1.dist-info/LICENSE
django_rest_choices-0.0.1.dist-info/METADATA
django_rest_choices-0.0.1.dist-info/WHEEL
django_rest_choices-0.0.1.dist-info/top_level.txt
django_rest_choices-0.0.1.dist-info/RECORD
